[
    {
        "id": 901,
        "polish": "niewychowany",
        "spanish": "maleducado"
    },
    {
        "id": 902,
        "polish": "zły",
        "spanish": "malo"
    },
    {
        "id": 903,
        "polish": "jabłko",
        "spanish": "manzanas"
    },
    {
        "id": 904,
        "polish": "cudowny, wspaniały",
        "spanish": "maravilloso"
    },
    {
        "id": 905,
        "polish": "brązowy",
        "spanish": "marrón"
    },
    {
        "id": 906,
        "polish": "więcej, bardziej",
        "spanish": "más"
    },
    {
        "id": 907,
        "polish": "później",
        "spanish": "más tarde"
    },
    {
        "id": 908,
        "polish": "zabijać",
        "spanish": "matar"
    },
    {
        "id": 909,
        "polish": "starszy",
        "spanish": "mayor"
    },
    {
        "id": 910,
        "polish": "większość",
        "spanish": "mayoria"
    },
    {
        "id": 911,
        "polish": "mnie, mi",
        "spanish": "me"
    },
    {
        "id": 912,
        "polish": "pół",
        "spanish": "medio "
    },
    {
        "id": 913,
        "polish": "lepiej",
        "spanish": "mejor"
    },
    {
        "id": 914,
        "polish": "młodszy",
        "spanish": "menor"
    },
    {
        "id": 915,
        "polish": "mniej",
        "spanish": "menos"
    },
    {
        "id": 916,
        "polish": "kłamać",
        "spanish": "mentir"
    },
    {
        "id": 917,
        "polish": "mój, moja, moje",
        "spanish": "mi"
    },
    {
        "id": 918,
        "polish": "podczas gdy",
        "spanish": "mientras"
    },
    {
        "id": 919,
        "polish": "tysiąc",
        "spanish": "mil"
    },
    {
        "id": 920,
        "polish": "minimalny, najmniejszy",
        "spanish": "minimo"
    },
    {
        "id": 921,
        "polish": "patrzeć, oglądać",
        "spanish": "mirar"
    },
    {
        "id": 922,
        "polish": "nowoczesny",
        "spanish": "moderno"
    },
    {
        "id": 923,
        "polish": "przeszkadzać, dokuczać",
        "spanish": "molestar"
    },
    {
        "id": 924,
        "polish": "fioletowy",
        "spanish": "morado"
    },
    {
        "id": 925,
        "polish": "umierać",
        "spanish": "morir"
    },
    {
        "id": 926,
        "polish": "ruszać, przesuwać, poruszać",
        "spanish": "mover"
    },
    {
        "id": 927,
        "polish": "bardzo, dużo",
        "spanish": "mucho"
    },
    {
        "id": 928,
        "polish": "dużo czasu, długo",
        "spanish": "mucho tiemo"
    },
    {
        "id": 929,
        "polish": "nieżywy",
        "spanish": "muerto"
    },
    {
        "id": 930,
        "polish": "kolorowy",
        "spanish": "multicolor"
    },
    {
        "id": 931,
        "polish": "bardzo",
        "spanish": "muy"
    },
    {
        "id": 932,
        "polish": "nic",
        "spanish": "nada"
    },
    {
        "id": 933,
        "polish": "pływać",
        "spanish": "nadar"
    },
    {
        "id": 934,
        "polish": "nikt",
        "spanish": "nadie"
    },
    {
        "id": 935,
        "polish": "pomarańczowy",
        "spanish": "naranja"
    },
    {
        "id": 936,
        "polish": "naturalny",
        "spanish": "natural"
    },
    {
        "id": 937,
        "polish": "oczywiście, naturalnie",
        "spanish": "naturalmente"
    },
    {
        "id": 938,
        "polish": "potrzebny",
        "spanish": "necesario"
    },
    {
        "id": 939,
        "polish": "potrzebować",
        "spanish": "necesitar"
    },
    {
        "id": 940,
        "polish": "czarny ",
        "spanish": "negro"
    },
    {
        "id": 941,
        "polish": "ani… ani",
        "spanish": "ni… ni"
    },
    {
        "id": 942,
        "polish": "żaden",
        "spanish": "ningún"
    },
    {
        "id": 943,
        "polish": "nie",
        "spanish": "no"
    },
    {
        "id": 944,
        "polish": "zazwyczaj, na ogół",
        "spanish": "normalmente"
    },
    {
        "id": 945,
        "polish": "my",
        "spanish": "nosotros, nosotras"
    },
    {
        "id": 946,
        "polish": "dziewięćset",
        "spanish": "novecientos"
    },
    {
        "id": 947,
        "polish": "dziewiąty",
        "spanish": "noveno"
    },
    {
        "id": 948,
        "polish": "dziewięćdziesiąt",
        "spanish": "noventa"
    },
    {
        "id": 949,
        "polish": "dziewięćdziesiąt pięć",
        "spanish": "noventa y cinco"
    },
    {
        "id": 950,
        "polish": "dziewięćdziesiąt cztery",
        "spanish": "noventa y cuatro"
    }
]